bpycv/__info__.py
bpycv/__init__.py
bpycv/camera_utils.py
bpycv/domain_randomzition.py
bpycv/exr_image_parser.py
bpycv/hdri_manager.py
bpycv/material_utils.py
bpycv/node_graph.py
bpycv/object_utils.py
bpycv/physic_utils.py
bpycv/pose_utils.py
bpycv/pseudo_color.py
bpycv/render_utils.py
bpycv/scene_setting.py
bpycv/select_utils.py
bpycv/statu_recover.py
bpycv/stereo_utils.py
bpycv/utils.py
bpycv/dataset_utils/__init__.py
bpycv/dataset_utils/cfg_utils.py
bpycv/dataset_utils/dataset_generator.py
bpycv-1.0.0.dist-info/licenses/LICENSE
bpycv-1.0.0.dist-info/METADATA
bpycv-1.0.0.dist-info/WHEEL
bpycv-1.0.0.dist-info/top_level.txt
bpycv-1.0.0.dist-info/RECORD
