Metadata-Version: 2.4
Name: bpycv
Version: 1.0.0
Summary: Computer vision utils for Blender.
Home-page: https://github.com/DIYer22/bpycv
Author: DIYer22
Author-email: ylxx@live.com
Classifier: Topic :: Scientific/Engineering :: Artificial Intelligence
Classifier: Topic :: Multimedia :: Graphics :: 3D Rendering
Classifier: Topic :: Multimedia :: Graphics :: 3D Modeling
Classifier: Topic :: Software Development :: Libraries :: Python Modules
Classifier: Programming Language :: Python :: 3
Classifier: License :: OSI Approved :: MIT License
Classifier: Operating System :: OS Independent
Classifier: Intended Audience :: Developers
Classifier: Intended Audience :: Science/Research
Requires-Python: >=3.6
License-File: LICENSE
Requires-Dist: minexr
Requires-Dist: boxx>=0.10.0
Requires-Dist: beautifulsoup4
Requires-Dist: requests
Requires-Dist: opencv-python
Dynamic: author
Dynamic: author-email
Dynamic: classifier
Dynamic: description
Dynamic: description-content-type
Dynamic: home-page
Dynamic: license-file
Dynamic: requires-dist
Dynamic: requires-python
Dynamic: summary
